slidingRP/Fig2_ACGMetric.py
slidingRP/Fig3_simulations.py
slidingRP/Fig4_HillCompConfidence.py
slidingRP/Fig5_ConfROC.py
slidingRP/Fig6_drift.py
slidingRP/__init__.py
slidingRP/loadSaveData.py
slidingRP/metrics.py
slidingRP/scriptSavePaperFigs.py
slidingRP/simulations.py
slidingRP/spike_sorting_benchmark.py
slidingRP-1.1.1.dist-info/METADATA
slidingRP-1.1.1.dist-info/WHEEL
slidingRP-1.1.1.dist-info/top_level.txt
slidingRP-1.1.1.dist-info/RECORD
