Metadata-Version: 2.1
Name: slidingRP
Version: 1.1.1
Summary: Quality metric from spike trains
Home-page: https://github.com/SteinmetzLab/slidingRefractory
Author: Noam Roth
Project-URL: Bug Tracker, https://github.com/SteinmetzLab/slidingRefractory/issues
Classifier: Programming Language :: Python :: 3
Classifier: License :: OSI Approved :: MIT License
Classifier: Operating System :: OS Independent
Requires-Python: >=3.8
